fhnw_ds_hs2019_weatherstation_api/__init__.py
fhnw_ds_hs2019_weatherstation_api/data_import.py
fhnw_ds_hs2019_weatherstation_api-0.21.dist-info/METADATA
fhnw_ds_hs2019_weatherstation_api-0.21.dist-info/WHEEL
fhnw_ds_hs2019_weatherstation_api-0.21.dist-info/top_level.txt
fhnw_ds_hs2019_weatherstation_api-0.21.dist-info/RECORD
