Metadata-Version: 2.1
Name: fhnw-ds-hs2019-weatherstation-api
Version: 0.21
Summary: Provides access to the Wasserschutzpolizei Zurich live and historic weather data.
Home-page: http://github.com/markif/WeatherStation_HS2019
Author: Fabian
License: MIT
Platform: UNKNOWN
Requires-Dist: pandas (<0.24)
Requires-Dist: influxdb
Requires-Dist: requests
Requires-Dist: tzlocal
Requires-Dist: pytz
